README.md
setup.py
ota/__init__.py
ota/main.py
ota.egg-info/PKG-INFO
ota.egg-info/SOURCES.txt
ota.egg-info/dependency_links.txt
ota.egg-info/entry_points.txt
ota.egg-info/requires.txt
ota.egg-info/top_level.txt
ota/cli/__init__.py
ota/cli/analyze.py
ota/cli/config.py
ota/cli/download.py
ota/cli/inspect.py
ota/cli/send.py
ota/core/__init__.py
ota/core/analyze.py
ota/core/console.py
ota/core/models.py
ota/core/rpc.py
ota/core/settings.py
ota/core/tools.py
ota/odoo/__init__.py
ota/odoo/field.py
ota/odoo/model.py
ota/odoo/module.py