Metadata-Version: 2.1
Name: ota
Version: 0.1.1
Summary: Odoo Technical Analysis
Home-page: https://github.com/royaurelien/ota-client
Author: Aurelien ROY
Author-email: roy.aurelien@gmail.com
License: BSD 2-clause
